[
  {
    "id": 1,
    "slug": "item-one",
    "title": "Item One",
    "description": "Description for Item One",
    "price": 29.99
  },
  {
    "id": 2,
    "slug": "item-two",
    "title": "Item Two",
    "description": "Description for Item Two",
    "price": 39.99
  },
  {
    "id": 3,
    "slug": "item-three",
    "title": "Item Three",
    "description": "Description for Item Three",
    "price": 49.99
  },
  {
    "id": 4,
    "slug": "item-four",
    "title": "Item Four",
    "description": "Description for Item Four",
    "price": 59.99
  },
  {
    "id": 5,
    "slug": "item-five",
    "title": "Item Five",
    "description": "Description for Item Five",
    "price": 69.99
  }
]
